easyrabbit/__init__.py
easyrabbit/basic_routing.py
easyrabbit-0.0.3.dist-info/DESCRIPTION.rst
easyrabbit-0.0.3.dist-info/METADATA
easyrabbit-0.0.3.dist-info/RECORD
easyrabbit-0.0.3.dist-info/WHEEL
easyrabbit-0.0.3.dist-info/metadata.json
easyrabbit-0.0.3.dist-info/top_level.txt
