Metadata-Version: 2.0
Name: easyrabbit
Version: 0.0.3
Summary: Easy utilities for common RabbitMQ tasks
Home-page: https://github.com/scnerd/easyrabbit
Author: scnerd
Author-email: UNKNOWN
License: MIT
Platform: UNKNOWN
Requires-Dist: pika (>=0.10)
